telebot_constructor/__init__.py
telebot_constructor/app.py
telebot_constructor/app_models.py
telebot_constructor/auth/__init__.py
telebot_constructor/auth/auth.py
telebot_constructor/auth/telegram_auth.py
telebot_constructor/bot_config.py
telebot_constructor/build_time_config.py
telebot_constructor/client/__init__.py
telebot_constructor/client/bot.py
telebot_constructor/client/client.py
telebot_constructor/constants.py
telebot_constructor/construct.py
telebot_constructor/cors.py
telebot_constructor/data/prefilled_messages.json
telebot_constructor/debug.py
telebot_constructor/group_chat_discovery.py
telebot_constructor/py.typed
telebot_constructor/runners.py
telebot_constructor/static/assets/ContrastTheme-B2fvkEhQ.js
telebot_constructor/static/assets/Controls-BDGotJ5f.js
telebot_constructor/static/assets/DrawerController-CISsbVWm.js
telebot_constructor/static/assets/DrawerController-CTiaKYtA.css
telebot_constructor/static/assets/Icon-BH0eb8S4.js
telebot_constructor/static/assets/Minimap-D8FUOXMK.js
telebot_constructor/static/assets/ThemeToggle-5x_Mw_X4.js
telebot_constructor/static/assets/index-BmyGLf-x.js
telebot_constructor/static/assets/index-D1pUN9Ss.css
telebot_constructor/static/cta-desktop-en.png
telebot_constructor/static/cta-mobile-en.png
telebot_constructor/static/favicon.svg
telebot_constructor/static/group_chat_auth_login.html
telebot_constructor/static/icons/feedback.svg
telebot_constructor/static/icons/form.svg
telebot_constructor/static/icons/github.svg
telebot_constructor/static/icons/integration.svg
telebot_constructor/static/icons/knowledge_base.svg
telebot_constructor/static/icons/multilang.svg
telebot_constructor/static/icons/pallette.svg
telebot_constructor/static/icons/privacy.svg
telebot_constructor/static/icons/statistics.svg
telebot_constructor/static/icons/telegram-dark.svg
telebot_constructor/static/icons/template.svg
telebot_constructor/static/icons/visual.svg
telebot_constructor/static/index.html
telebot_constructor-0.2.19.dist-info/LICENSE
telebot_constructor-0.2.19.dist-info/METADATA
telebot_constructor-0.2.19.dist-info/WHEEL
telebot_constructor-0.2.19.dist-info/RECORD
