Metadata-Version: 2.1
Name: telebot-constructor
Version: 0.2.19
Summary: No-code Telegram bot constructor
License: GPL-3
Author: Igor Vaiman
Author-email: gosha.vaiman@gmail.com
Requires-Python: >=3.12,<4.0
Classifier: License :: Other/Proprietary License
Classifier: Programming Language :: Python :: 3
Classifier: Programming Language :: Python :: 3.12
Requires-Dist: aiobotocore (>=2.15.2,<3.0.0)
Requires-Dist: aiohttp (>=3.11.6,<4.0.0)
Requires-Dist: aiohttp-swagger (>=1.0.16,<2.0.0)
Requires-Dist: cachetools (>=5.3.1,<6.0.0)
Requires-Dist: cryptography (>=44.0.1,<45.0.0)
Requires-Dist: pillow (>=10.3.0,<11.0.0)
Requires-Dist: pydantic (>=2.8.2,<3.0.0)
Requires-Dist: python-slugify (>=8.0.4,<9.0.0)
Requires-Dist: telebot-against-war (>=0.7.12,<0.8.0)
Requires-Dist: telebot-components (>=0.16.0,<0.17.0)
Requires-Dist: telegramify-markdown (>=0.5.1,<0.6.0)
Requires-Dist: urllib3 (>=1.26.18,<2.0.0)
